.gitignore
MANIFEST.in
README.rst
bootstrap.py
buildout.cfg
collective.diggdigg-configure.zcml
setup.py
collective/__init__.py
collective.diggdigg.egg-info/PKG-INFO
collective.diggdigg.egg-info/SOURCES.txt
collective.diggdigg.egg-info/dependency_links.txt
collective.diggdigg.egg-info/entry_points.txt
collective.diggdigg.egg-info/namespace_packages.txt
collective.diggdigg.egg-info/not-zip-safe
collective.diggdigg.egg-info/requires.txt
collective.diggdigg.egg-info/top_level.txt
collective/diggdigg/__init__.py
collective/diggdigg/configure.zcml
collective/diggdigg/diggdigg.pt
collective/diggdigg/layer.py
collective/diggdigg/rebuild_i18n.sh
collective/diggdigg/settings.py
collective/diggdigg/test.js
collective/diggdigg/testing.py
collective/diggdigg/upgrades.py
collective/diggdigg/upgrades.zcml
collective/diggdigg/viewlets.py
collective/diggdigg/buttons/__init__.py
collective/diggdigg/buttons/bufferapp.py
collective/diggdigg/buttons/button.py
collective/diggdigg/buttons/configure.zcml
collective/diggdigg/buttons/facebook.py
collective/diggdigg/buttons/flattr.py
collective/diggdigg/buttons/google.py
collective/diggdigg/buttons/linkedin.py
collective/diggdigg/buttons/pinterest.py
collective/diggdigg/buttons/reddit.py
collective/diggdigg/buttons/twitter.py
collective/diggdigg/buttons/viadeo.py
collective/diggdigg/locales/collective.diggdigg.pot
collective/diggdigg/locales/en/LC_MESSAGES/collective.diggdigg.po
collective/diggdigg/locales/fr/LC_MESSAGES/collective.diggdigg.po
collective/diggdigg/profiles/default/browserlayer.xml
collective/diggdigg/profiles/default/cssregistry.xml
collective/diggdigg/profiles/default/jsregistry.xml
collective/diggdigg/profiles/default/metadata.xml
collective/diggdigg/profiles/default/registry.xml
collective/diggdigg/resources/.gitignore
collective/diggdigg/resources/css/diggdigg-style-admin.css
collective/diggdigg/resources/css/diggdigg-style.css
collective/diggdigg/resources/image/LeoWid.png
collective/diggdigg/resources/image/ajax-loader.gif
collective/diggdigg/resources/image/comments-count.png
collective/diggdigg/resources/image/comments-link.png
collective/diggdigg/resources/image/comments.png
collective/diggdigg/resources/image/delicious-compact.png
collective/diggdigg/resources/image/delicious.png
collective/diggdigg/resources/image/email.png
